README.md
setup.py
pulumi_huaweicloud/__init__.py
pulumi_huaweicloud/_inputs.py
pulumi_huaweicloud/_utilities.py
pulumi_huaweicloud/get_availability_zones.py
pulumi_huaweicloud/provider.py
pulumi_huaweicloud/pulumi-plugin.json
pulumi_huaweicloud/py.typed
pulumi_huaweicloud.egg-info/PKG-INFO
pulumi_huaweicloud.egg-info/SOURCES.txt
pulumi_huaweicloud.egg-info/dependency_links.txt
pulumi_huaweicloud.egg-info/not-zip-safe
pulumi_huaweicloud.egg-info/requires.txt
pulumi_huaweicloud.egg-info/top_level.txt
pulumi_huaweicloud/advancedantiddos/__init__.py
pulumi_huaweicloud/advancedantiddos/forward_rule.py
pulumi_huaweicloud/antiddos/__init__.py
pulumi_huaweicloud/antiddos/basic.py
pulumi_huaweicloud/antiddos/get_antiddos.py
pulumi_huaweicloud/aom/__init__.py
pulumi_huaweicloud/aom/_inputs.py
pulumi_huaweicloud/aom/alarm_rule.py
pulumi_huaweicloud/aom/outputs.py
pulumi_huaweicloud/aom/service_discovery_rule.py
pulumi_huaweicloud/as_/__init__.py
pulumi_huaweicloud/as_/_inputs.py
pulumi_huaweicloud/as_/bandwidth_policy.py
pulumi_huaweicloud/as_/configuration.py
pulumi_huaweicloud/as_/group.py
pulumi_huaweicloud/as_/lifecycle_hook.py
pulumi_huaweicloud/as_/outputs.py
pulumi_huaweicloud/as_/policy.py
pulumi_huaweicloud/bcs/__init__.py
pulumi_huaweicloud/bcs/_inputs.py
pulumi_huaweicloud/bcs/instance.py
pulumi_huaweicloud/bcs/outputs.py
pulumi_huaweicloud/bms/__init__.py
pulumi_huaweicloud/bms/_inputs.py
pulumi_huaweicloud/bms/get_flavors.py
pulumi_huaweicloud/bms/instance.py
pulumi_huaweicloud/bms/outputs.py
pulumi_huaweicloud/cbr/__init__.py
pulumi_huaweicloud/cbr/_inputs.py
pulumi_huaweicloud/cbr/get_vaults.py
pulumi_huaweicloud/cbr/outputs.py
pulumi_huaweicloud/cbr/policy.py
pulumi_huaweicloud/cbr/vault.py
pulumi_huaweicloud/cc/__init__.py
pulumi_huaweicloud/cc/connection.py
pulumi_huaweicloud/cc/network_instance.py
pulumi_huaweicloud/cce/__init__.py
pulumi_huaweicloud/cce/_inputs.py
pulumi_huaweicloud/cce/addon.py
pulumi_huaweicloud/cce/chart.py
pulumi_huaweicloud/cce/cluster.py
pulumi_huaweicloud/cce/cluster_certificate_revoke.py
pulumi_huaweicloud/cce/cluster_log_config.py
pulumi_huaweicloud/cce/cluster_upgrade.py
pulumi_huaweicloud/cce/get_addon_template.py
pulumi_huaweicloud/cce/get_addons.py
