Metadata-Version: 2.1
Name: pulumi-huaweicloud
Version: 0.0.12
Summary: A Pulumi package for creating and managing Huaweicloud cloud resources.
Home-page: https://huaweicloud-pulumi-provider.readthedocs.io
License: Apache-2.0
Project-URL: Repository, https://github.com/huaweicloud/pulumi-huaweicloud
Keywords: pulumi huaweicloud category/cloud
Platform: UNKNOWN
